<?xml version="1.0" encoding="utf-8"?>
<TextureAtlas imagePath="mario64.png">
	<!-- Created with Adobe Animate version 21.0.0.35450 -->
	<!-- http://www.adobe.com/products/animate.html -->
	<SubTexture name="downsing instance 10000" x="0" y="0" width="1921" height="1080"/>
	<SubTexture name="downsing instance 10001" x="1931" y="0" width="1921" height="1080"/>
	<SubTexture name="downsing instance 10002" x="3862" y="0" width="1921" height="1080"/>
	<SubTexture name="downsing instance 10003" x="3862" y="0" width="1921" height="1080"/>
	<SubTexture name="downsing instance 10004" x="3862" y="0" width="1921" height="1080"/>
	<SubTexture name="downsing instance 10005" x="3862" y="0" width="1921" height="1080"/>
	<SubTexture name="downsing instance 10006" x="3862" y="0" width="1921" height="1080"/>
	<SubTexture name="downsing instance 10007" x="3862" y="0" width="1921" height="1080"/>
	<SubTexture name="downsing instance 10008" x="3862" y="0" width="1921" height="1080"/>
	<SubTexture name="downsing instance 10009" x="3862" y="0" width="1921" height="1080"/>
	<SubTexture name="downsing instance 10010" x="3862" y="0" width="1921" height="1080"/>
	<SubTexture name="downsing instance 10011" x="3862" y="0" width="1921" height="1080"/>
	<SubTexture name="downsing instance 10012" x="3862" y="0" width="1921" height="1080"/>
	<SubTexture name="downsing instance 10013" x="3862" y="0" width="1921" height="1080"/>
	<SubTexture name="idle instance 10000" x="5793" y="0" width="1997" height="1080"/>
	<SubTexture name="idle instance 10001" x="0" y="1090" width="1997" height="1080"/>
	<SubTexture name="idle instance 10002" x="2007" y="1090" width="1997" height="1080"/>
	<SubTexture name="idle instance 10003" x="4014" y="1090" width="1997" height="1080"/>
	<SubTexture name="idle instance 10004" x="6021" y="1090" width="1997" height="1080"/>
	<SubTexture name="idle instance 10005" x="0" y="2180" width="1997" height="1080"/>
	<SubTexture name="idle instance 10006" x="2007" y="2180" width="1997" height="1080"/>
	<SubTexture name="idle instance 10007" x="4014" y="2180" width="1997" height="1080"/>
	<SubTexture name="idle instance 10008" x="6021" y="2180" width="1997" height="1080"/>
	<SubTexture name="idle instance 10009" x="6021" y="2180" width="1997" height="1080"/>
	<SubTexture name="idle instance 10010" x="6021" y="2180" width="1997" height="1080"/>
	<SubTexture name="idle instance 10011" x="6021" y="2180" width="1997" height="1080"/>
	<SubTexture name="idle instance 10012" x="0" y="3270" width="1997" height="1080"/>
	<SubTexture name="idle instance 10013" x="6021" y="1090" width="1997" height="1080"/>
	<SubTexture name="leftsing instance 10000" x="2007" y="3270" width="1920" height="1080"/>
	<SubTexture name="leftsing instance 10001" x="3937" y="3270" width="1920" height="1080"/>
	<SubTexture name="leftsing instance 10002" x="5867" y="3270" width="1920" height="1080"/>
	<SubTexture name="leftsing instance 10003" x="5867" y="3270" width="1920" height="1080"/>
	<SubTexture name="leftsing instance 10004" x="5867" y="3270" width="1920" height="1080"/>
	<SubTexture name="leftsing instance 10005" x="5867" y="3270" width="1920" height="1080"/>
	<SubTexture name="leftsing instance 10006" x="5867" y="3270" width="1920" height="1080"/>
	<SubTexture name="leftsing instance 10007" x="5867" y="3270" width="1920" height="1080"/>
	<SubTexture name="leftsing instance 10008" x="5867" y="3270" width="1920" height="1080"/>
	<SubTexture name="leftsing instance 10009" x="5867" y="3270" width="1920" height="1080"/>
	<SubTexture name="leftsing instance 10010" x="5867" y="3270" width="1920" height="1080"/>
	<SubTexture name="leftsing instance 10011" x="5867" y="3270" width="1920" height="1080"/>
	<SubTexture name="leftsing instance 10012" x="5867" y="3270" width="1920" height="1080"/>
	<SubTexture name="leftsing instance 10013" x="5867" y="3270" width="1920" height="1080"/>
	<SubTexture name="rightsing instance 10000" x="0" y="4360" width="1938" height="1125"/>
	<SubTexture name="rightsing instance 10001" x="1948" y="4360" width="1938" height="1125"/>
	<SubTexture name="rightsing instance 10002" x="3896" y="4360" width="1938" height="1125"/>
	<SubTexture name="rightsing instance 10003" x="3896" y="4360" width="1938" height="1125"/>
	<SubTexture name="rightsing instance 10004" x="3896" y="4360" width="1938" height="1125"/>
	<SubTexture name="rightsing instance 10005" x="3896" y="4360" width="1938" height="1125"/>
	<SubTexture name="rightsing instance 10006" x="3896" y="4360" width="1938" height="1125"/>
	<SubTexture name="rightsing instance 10007" x="3896" y="4360" width="1938" height="1125"/>
	<SubTexture name="rightsing instance 10008" x="3896" y="4360" width="1938" height="1125"/>
	<SubTexture name="rightsing instance 10009" x="3896" y="4360" width="1938" height="1125"/>
	<SubTexture name="rightsing instance 10010" x="3896" y="4360" width="1938" height="1125"/>
	<SubTexture name="rightsing instance 10011" x="3896" y="4360" width="1938" height="1125"/>
	<SubTexture name="rightsing instance 10012" x="3896" y="4360" width="1938" height="1125"/>
	<SubTexture name="rightsing instance 10013" x="3896" y="4360" width="1938" height="1125"/>
	<SubTexture name="upsing instance 10000" x="5844" y="4360" width="1940" height="1080"/>
	<SubTexture name="upsing instance 10001" x="0" y="5495" width="1940" height="1080"/>
	<SubTexture name="upsing instance 10002" x="1950" y="5495" width="1940" height="1080"/>
	<SubTexture name="upsing instance 10003" x="1950" y="5495" width="1940" height="1080"/>
	<SubTexture name="upsing instance 10004" x="1950" y="5495" width="1940" height="1080"/>
	<SubTexture name="upsing instance 10005" x="1950" y="5495" width="1940" height="1080"/>
	<SubTexture name="upsing instance 10006" x="1950" y="5495" width="1940" height="1080"/>
	<SubTexture name="upsing instance 10007" x="1950" y="5495" width="1940" height="1080"/>
	<SubTexture name="upsing instance 10008" x="1950" y="5495" width="1940" height="1080"/>
	<SubTexture name="upsing instance 10009" x="1950" y="5495" width="1940" height="1080"/>
	<SubTexture name="upsing instance 10010" x="1950" y="5495" width="1940" height="1080"/>
	<SubTexture name="upsing instance 10011" x="1950" y="5495" width="1940" height="1080"/>
	<SubTexture name="upsing instance 10012" x="1950" y="5495" width="1940" height="1080"/>
	<SubTexture name="upsing instance 10013" x="1950" y="5495" width="1940" height="1080"/>
</TextureAtlas>
